soie/__init__.py
soie/applications.py
soie/exceptions.py
soie/requests.py
soie/responses.py
soie/routing.py
soie/status.py
soie/types.py
soie/views.py
soie-0.1.0.dist-info/WHEEL
soie-0.1.0.dist-info/METADATA
soie-0.1.0.dist-info/LICENSE
soie-0.1.0.dist-info/RECORD
